LICENSE
MANIFEST.in
README.md
pyproject.toml
src/metamist/__init__.py
src/metamist/api_client.py
src/metamist/configuration.py
src/metamist/exceptions.py
src/metamist/model_utils.py
src/metamist/rest.py
src/metamist.egg-info/PKG-INFO
src/metamist.egg-info/SOURCES.txt
src/metamist.egg-info/dependency_links.txt
src/metamist.egg-info/entry_points.txt
src/metamist.egg-info/requires.txt
src/metamist.egg-info/top_level.txt
src/metamist/api/__init__.py
src/metamist/api/analysis_api.py
src/metamist/api/analysis_runner_api.py
src/metamist/api/assay_api.py
src/metamist/api/billing_api.py
src/metamist/api/cohort_api.py
src/metamist/api/enums_api.py
src/metamist/api/family_api.py
src/metamist/api/import_api.py
src/metamist/api/participant_api.py
src/metamist/api/project_api.py
src/metamist/api/project_insights_api.py
src/metamist/api/sample_api.py
src/metamist/api/seqr_api.py
src/metamist/api/sequencing_group_api.py
src/metamist/api/web_api.py
src/metamist/apis/__init__.py
src/metamist/audit/__init__.py
src/metamist/audit/adapters/__init__.py
src/metamist/audit/adapters/graphql_client.py
src/metamist/audit/adapters/storage_client.py
src/metamist/audit/cli/__init__.py
src/metamist/audit/cli/delete_from_audit_results.py
src/metamist/audit/cli/review_audit_results.py
src/metamist/audit/cli/upload_bucket_audit.py
src/metamist/audit/data_access/__init__.py
src/metamist/audit/data_access/gcs_data_access.py
src/metamist/audit/data_access/metamist_data_access.py
src/metamist/audit/models/__init__.py
src/metamist/audit/models/entities.py
src/metamist/audit/models/value_objects.py
src/metamist/audit/services/__init__.py
src/metamist/audit/services/audit_analyzer.py
src/metamist/audit/services/audit_logging.py
src/metamist/audit/services/file_matcher.py
src/metamist/audit/services/reporter.py
src/metamist/graphql/__init__.py
src/metamist/graphql/schema.graphql
src/metamist/model/__init__.py
src/metamist/model/analysis.py
src/metamist/model/analysis_cost_record.py
src/metamist/model/analysis_cost_record_batch.py
src/metamist/model/analysis_cost_record_batch_job.py
src/metamist/model/analysis_cost_record_category.py
src/metamist/model/analysis_cost_record_cromwell_subworkflow.py
