Metadata-Version: 2.4
Name: metamist
Version: 7.13.4
Summary: Python API for interacting with the Sample API system
License-Expression: MIT
Project-URL: Homepage, https://github.com/populationgenomics/metamist
Keywords: bioinformatics
Classifier: Environment :: Console
Classifier: Intended Audience :: Science/Research
Classifier: Natural Language :: English
Classifier: Operating System :: MacOS :: MacOS X
Classifier: Operating System :: POSIX
Classifier: Operating System :: Unix
Classifier: Programming Language :: Python
Classifier: Topic :: Scientific/Engineering
Classifier: Topic :: Scientific/Engineering :: Bio-Informatics
Requires-Python: >=3.10
License-File: LICENSE
Requires-Dist: backoff>=2.2.1
Requires-Dist: click
Requires-Dist: google-auth
Requires-Dist: google-api-core
Requires-Dist: urllib3>=1.25.3
Requires-Dist: python-dateutil
Requires-Dist: requests
Requires-Dist: cpg-utils>=5.0.5
Requires-Dist: gql[aiohttp,requests]~=3.5
Requires-Dist: tabulate>=0.9.0
Dynamic: license-file
